LICENSE
MANIFEST.in
README.txt
setup.py
mnamr/__init__.py
mnamr/exceptions.py
mnamr/imdb_search.py
mnamr/mnamr.py
mnamr/models.py
mnamr/paginator.py
mnamr.egg-info/PKG-INFO
mnamr.egg-info/SOURCES.txt
mnamr.egg-info/dependency_links.txt
mnamr.egg-info/entry_points.txt
mnamr.egg-info/requires.txt
mnamr.egg-info/top_level.txt