Metadata-Version: 1.0
Name: mnamr
Version: 0.1.3
Summary: Movie folder renamer
Home-page: https://pypi.python.org/pypi/mnamr/
Author: Ali Kaafarani
Author-email: ali@kvikshaug.no
License: MIT
Platform: UNKNOWN
